cerbi_python_logging_governance/__init__.py
cerbi_python_logging_governance/constants.py
cerbi_python_logging_governance/evaluator.py
cerbi_python_logging_governance/filter.py
cerbi_python_logging_governance/handler.py
cerbi_python_logging_governance/loader.py
cerbi_python_logging_governance/models.py
cerbi_python_logging_governance/queue_handler.py
cerbi_python_logging_governance-0.1.0a0.dist-info/licenses/LICENSE
cerbi_python_logging_governance-0.1.0a0.dist-info/METADATA
cerbi_python_logging_governance-0.1.0a0.dist-info/WHEEL
cerbi_python_logging_governance-0.1.0a0.dist-info/top_level.txt
cerbi_python_logging_governance-0.1.0a0.dist-info/RECORD
