Metadata-Version: 2.4
Name: cerbi-python-logging-governance
Version: 0.1.0a0
Summary: Cerbi governance runtime plugin for Python logging - PII redaction, scoring, and compliance
Author-email: Cerbi <governance@cerbi.io>
License: MIT
Project-URL: Homepage, https://cerbi.io
Project-URL: Documentation, https://cerbi.io/docs/python-logging
Project-URL: Repository, https://github.com/cerbi-io/cerbi-python-logging-governance
Project-URL: Issues, https://github.com/cerbi-io/cerbi-python-logging-governance/issues
Keywords: logging,governance,cerbi,pii,redaction,compliance,scoring
Classifier: Development Status :: 3 - Alpha
Classifier: Programming Language :: Python :: 3
Classifier: Programming Language :: Python :: 3.11
Classifier: Programming Language :: Python :: 3.12
Classifier: Programming Language :: Python :: 3.13
Classifier: License :: OSI Approved :: MIT License
Classifier: Operating System :: OS Independent
Classifier: Intended Audience :: Developers
Classifier: Topic :: System :: Logging
Classifier: Topic :: Security
Requires-Python: >=3.11
License-File: LICENSE
Dynamic: license-file
